setup.py
pypi_test_fiveplus/__init__.py
pypi_test_fiveplus/test.py
pypi_test_fiveplus.egg-info/PKG-INFO
pypi_test_fiveplus.egg-info/SOURCES.txt
pypi_test_fiveplus.egg-info/dependency_links.txt
pypi_test_fiveplus.egg-info/top_level.txt